setup.cfg
setup.py
Token/__init__.py
Token.egg-info/PKG-INFO
Token.egg-info/SOURCES.txt
Token.egg-info/dependency_links.txt
Token.egg-info/requires.txt
Token.egg-info/top_level.txt
Token/api/__init__.py
Token/api/account.py
Token/api/alias_service.py
Token/api/bank_service.py
Token/api/common.py
Token/api/member.py
Token/api/principal.py
Token/api/provider_service.py
Token/demos/__init__.py
Token/demos/demo1.py
Token/demos/demo2.py
Token/demos/prod-demo1.py
Token/demos/stg-demo1.py
Token/generated/__init__.py
Token/generated/alias/__init__.py
Token/generated/alias/api_client.py
Token/generated/alias/configuration.py
Token/generated/alias/rest.py
Token/generated/alias/setup.py
Token/generated/alias/apis/__init__.py
Token/generated/alias/apis/aliases_api.py
Token/generated/alias/apis/system_api.py
Token/generated/alias/models/__init__.py
Token/generated/alias/models/create_alias_request.py
Token/generated/alias/models/create_alias_response.py
Token/generated/alias/models/function1_request_context_boxed_unit.py
Token/generated/alias/models/get_alias_response.py
Token/generated/alias/models/system_check_response.py
Token/generated/alias/models/system_information_response.py
Token/generated/alias/models/system_information_response_dependency.py
Token/generated/alias/models/system_state_response.py
Token/generated/alias/models/system_state_response_property.py
Token/generated/bank/__init__.py
Token/generated/bank/api_client.py
Token/generated/bank/configuration.py
Token/generated/bank/rest.py
Token/generated/bank/setup.py
Token/generated/bank/apis/__init__.py
Token/generated/bank/apis/accesses_api.py
Token/generated/bank/apis/clients_api.py
Token/generated/bank/apis/system_api.py
Token/generated/bank/models/__init__.py
Token/generated/bank/models/balance.py
Token/generated/bank/models/create_access_request.py
Token/generated/bank/models/create_access_response.py
Token/generated/bank/models/create_transfer_request.py
Token/generated/bank/models/create_transfer_response.py
Token/generated/bank/models/create_transfer_response_counterparty.py
Token/generated/bank/models/function1_request_context_boxed_unit.py
