Metadata-Version: 1.0
Name: Token
Version: 1.8.2
Summary: Token client to REST Apis
Home-page: UNKNOWN
Author: Mariano Sorgente
Author-email: mariano.sorgente@token.io
License: UNKNOWN
Keywords: Swagger,Token API
Platform: UNKNOWN
